setup.py
lglass/__init__.py
lglass/bird.py
lglass/dns.py
lglass/route.py
lglass/rpsl.py
lglass/whoisd.py
lglass.egg-info/PKG-INFO
lglass.egg-info/SOURCES.txt
lglass.egg-info/dependency_links.txt
lglass.egg-info/entry_points.txt
lglass.egg-info/requires.txt
lglass.egg-info/top_level.txt
lglass/database/__init__.py
lglass/database/base.py
lglass/database/cache.py
lglass/database/cidr.py
lglass/database/file.py
lglass/database/lmdb.py
lglass/database/mongodb.py
lglass/database/redis.py
lglass/database/schema.py
lglass/database/sqlite3.py
lglass/database/whois.py
lglass/generators/__init__.py
lglass/generators/dns.py
lglass/generators/dot.py
lglass/generators/roa.py
lglass/schemas/as-block
lglass/schemas/as-set
lglass/schemas/aut-num
lglass/schemas/domain
lglass/schemas/filter-set
lglass/schemas/inet-rtr
lglass/schemas/inet6num
lglass/schemas/inetnum
lglass/schemas/irt
lglass/schemas/key-cert
lglass/schemas/mntner
lglass/schemas/organisation
lglass/schemas/peering-set
lglass/schemas/person
lglass/schemas/poem
lglass/schemas/poetic-form
lglass/schemas/role
lglass/schemas/route
lglass/schemas/route-set
lglass/schemas/route6
lglass/schemas/rtr-set
lglass/tools/bird.py
lglass/tools/regtool.py
lglass/tools/roagen.py
lglass/tools/zonegen.py
lglass/web/__init__.py
lglass/web/__main__.py
lglass/web/application.py
lglass/web/helpers.py
lglass/web/registry.py
lglass/web/templates/index.html
lglass/web/templates/layout.html
lglass/web/templates/registry/show_object.html
lglass/web/templates/registry/show_object_types.html
lglass/web/templates/registry/show_objects.html
lglass/web/templates/registry/whois_query.html