Metadata-Version: 1.1
Name: lglass
Version: 1.0.0b3
Summary: provides tools for registry maintenance
Home-page: https://github.com/fritz0705/lglass.git
Author: Fritz Grimpen
Author-email: fritz@grimpen.net
License: http://opensource.org/licenses/MIT
Platform: UNKNOWN
Classifier: Development Status :: 4 - Beta
Classifier: Operating System :: POSIX
Classifier: Programming Language :: Python :: 3.3
Classifier: Topic :: Internet :: Log Analysis
Classifier: Topic :: Internet :: WWW/HTTP :: WSGI :: Application
Classifier: Topic :: System :: Networking
Classifier: Topic :: System :: Systems Administration
